{"data_non_statistical":false,"graph_title":"Anzahl der Abholstellen f\u00fcr Produkte Solidarischer Landwirtschaft (SoLaWi)","graph_type":"line","indicator_number":"11.2.1","indicator_name":"Anzahl der Abholstellen f\u00fcr Produkte Solidarischer Landwirtschaft (SoLaWi)","indicator_sort_order":"11-02-01","published":true,"reporting_status":"complete","data_show_map":true,"national_geographical_coverage":"Treptow-K\u00f6penick","computation_units":"Anzahl der Abholstellen","source_active_1":true,"source_organisation_1":"Solidarsche Landwirtschaft (SoLaWi)","source_url_1":"https://www.solidarische-landwirtschaft.org/solawis-finden/karte/#/","source_url_text_1":"https://www.solidarische-landwirtschaft.org/solawis-finden/karte/#/","source_geographical_coverage_1":"Treptow-K\u00f6penick","sdg_goal":"11","target_name":"Ma\u00dfnahme - Vorantreibung der Ern\u00e4hrungswende regional","target_id":"11.2","page_content":"","national_metadata_update_url_text":"2021-08-11: see changes on GitHub","national_metadata_update_url":"https://github.com/beyersar/DataTK/commit/3b65b027479182bca324f49798d9990d7f9a41cd","national_data_update_url_text":"2021-08-11: see changes on GitHub","national_data_update_url":"https://github.com/beyersar/DataTK/commit/03af4b7b08d29e7fadb695261afc0e55f9b3c481","indicator":"11.2.1","language":"de"}