{"data_non_statistical":false,"graph_title":"Relative Luftbelastung in Treptow-K\u00f6penick","graph_type":"bar","indicator_number":"3.3.1.","indicator_name":"Relative Luftbelastung in Treptow-K\u00f6penick (Umweltgerechtigkeit)","indicator_sort_order":"03-03-01","published":true,"reporting_status":"complete","national_geographical_coverage":"Treptow-K\u00f6penick","computation_units":"Anzahl der Planungsr\u00e4ume","source_active_1":true,"source_organisation_1":"Senatsverwaltung f\u00fcr Umwelt, Verkehr und Klimaschutz","source_url_1":"https://www.berlin.de/sen/uvk/umwelt/nachhaltigkeit/umweltgerechtigkeit/","source_url_text_1":"https://www.berlin.de/sen/uvk/umwelt/nachhaltigkeit/umweltgerechtigkeit/","data_start_values":[{"field":"Relative Luftbelastung","value":"Gering"},{"field":"Relative Luftbelastung","value":"Mittel"},{"field":"Relative Luftbelastung","value":"Hoch"}],"page_content":"\nDer Indikator zeigt die relative Luftbelastung in Treptow-K\u00f6penick, also die Anzahl der gering, mittel und hoch belasteten Planungsr\u00e4ume (PLR) in Treptow-K\u00f6penick im Vergleich zu den Planungsr\u00e4umen anderer Bezirke Berlins. <br>\n\nUm einen Gesamt\u00fcberblick der Umweltbelastungen im Zusammenhang mit sozialer Gerechtigkeit in Berlin zu erhalten, hat das Land Berlin ein [Umweltgerechtigkeitsmonitoring](https://www.berlin.de/sen/uvk/umwelt/nachhaltigkeit/umweltgerechtigkeit/) implementiert. Das Umweltgerechtigkeitsmonitoring wertet vorhandene Daten verschiedener Kernindikatoren (e.g. L\u00e4rmbelastung und Luftverschmutzung) aus und aggregiert diese Daten auf Quartiersebene, beziehungsweise auf insgesamt 447 Planungsr\u00e4umen (PLR). Treptow-K\u00f6penick ist dabei in 34 Planungsr\u00e4ume unterteilt. <br>\n\nDie Datenbasis f\u00fcr die Luftbelastung der Planungsr\u00e4ume sind die fl\u00e4chengewichteten Jahresmittelwerte 2009 der Konzentration von Feinstaub (PM2,5) und Stickstoffdioxid (NO2). Anschlie\u00dfend wurden die ermittelten Werte in drei Kategorien unterteilt (gering: 79 PLR, mittel: 259 PLR, hoch: 109 PLR). <br>\n\nDie Bezirke sind dabei durch unterschiedlich stark von Luftbelastung betroffen. In Treptow-K\u00f6penick sind 1 PLR hoch, 21 PLR mittel und 12 PLR niedrig durch Luftverschmutzung belastet. <br> \n\nInsgesamt nimmt die Luftbelastung in Berlin von der Peripherie zum Zentrum zu. F\u00fcr PM2,5 lagen die Werte in dem geringstbelasteten Planungsraum bei 14,8 \u03bcg/m\u00b3 und in dem h\u00f6chstbelasteten Planungsraum bei 18,4 \u03bcg/m\u00b3, womit der von der Weltgesundheitsorganisation (WHO) empfohlene Richtwert von 10 \u03bcg/m\u00b3 in allen Planungsr\u00e4ume Berlins \u00fcberschritten wurde. Bei NO2 lagen die Werte zwischen 11,3 und 27,3 \u03bcg/m\u00b3 womit der WHO-Richtwert von 40 \u03bcg/m\u00b3 in keinem der Planungsr\u00e4ume \u00fcberschritten wurde.\n","national_metadata_updated_date":"2022-02-21","national_data_updated_date":"2021-07-16","national_metadata_update_url_text":"2022-02-21: see changes on GitHub","national_metadata_update_url":"https://github.com/SDGs-Treptow-Koepenick/DataTK/commit/4022ca5bd6147330c552a57b4d4c06836e798631","national_data_update_url_text":"2021-07-16: see changes on GitHub","national_data_update_url":"https://github.com/SDGs-Treptow-Koepenick/DataTK/commit/362f90ace206706b8a4ab0774e38aaccdce13a85","indicator":"3.3.1","target_id":"3.3","sdg_goal":"3","language":"de"}