{
  "resources": [
    {
      "path": "data.csv",
      "name": "data",
      "profile": "tabular-data-resource",
      "scheme": "file",
      "format": "csv",
      "hashing": "md5",
      "encoding": "utf-8",
      "schema": {
        "fields": [
          {
            "name": "Year",
            "type": "integer",
            "title": "Year"
          },
          {
            "name": "data.einewelt",
            "type": "string",
            "constraints": {
              "enum": [
                "City partnerships",
                "Parish projects",
                "School partnerships",
                "Civil society projects",
                "Fair Trade Shops",
                ""
              ]
            },
            "title": "One-World-Projects"
          },
          {
            "name": "Value",
            "type": "integer",
            "title": "Value"
          }
        ]
      }
    }
  ],
  "profile": "data-package",
  "name": "17-4-1",
  "title": "One world projects and partnerships in the Treptow-Köpenick district"
}