{"data_non_statistical":false,"graph_title":"Number of beekeepers in the district","graph_type":"bar","indicator_number":"11.2.2","indicator_name":"Number of beekeepers in the district","indicator_sort_order":"11-02-02","published":true,"reporting_status":"complete","national_geographical_coverage":"Treptow-K\u00f6penick","computation_units":"Absolute numbers","source_active_1":true,"source_organisation_1":"Veterin\u00e4ramt Treptow-K\u00f6penick","source_geographical_coverage_1":"Treptow-K\u00f6penick","sdg_goal":"11","target_name":"Measure - Promotion of the regional food system transition","target_id":"11.2","page_content":"\nThe indicator shows the number of beekeepers in the district. How many of these beekeepers are certified according to the EC organic regulation has yet to be determined.\n","de":{"language":"de","graph_title":"Number of beekeepers in the district","computation_units":"Absolute Zahlen","page_content":"\nDer Indikator zeigt die Anzahl der Imker im Bezirk. Wie viele dieser Imker nach der EG-\u00d6ko-Verordnung zertifiziert sind, muss noch ermittelt werden.\n"},"national_metadata_updated_date":"2021-09-28","national_data_updated_date":"2021-09-28","national_metadata_update_url_text":"2021-09-28: see changes on GitHub","national_metadata_update_url":"https://github.com/SDGs-Treptow-Koepenick/DataTK/commit/3bbb5bb3fcca86dc0b62c5bcb72c6301c0fbaed0","national_data_update_url_text":"2021-09-28: see changes on GitHub","national_data_update_url":"https://github.com/SDGs-Treptow-Koepenick/DataTK/commit/d17d28e0aa46a51c5291fe8d897a92d7f544d268","indicator":"11.2.2"}